uptrain/__init__.py
uptrain/__init__.pyi
uptrain/cli.py
uptrain/dashboard/backend/app.py
uptrain/dashboard/backend/nest_asyncio.py
uptrain/framework/__init__.py
uptrain/framework/__init__.pyi
uptrain/framework/base.py
uptrain/framework/builtins.py
uptrain/framework/checks.py
uptrain/framework/evalllm.py
uptrain/framework/evals.py
uptrain/framework/rca_templates.py
uptrain/framework/remote.py
uptrain/framework/signal.py
uptrain/framework/eval_assistant/__init__.py
uptrain/framework/eval_assistant/assistant_evals_prompts.py
uptrain/framework/eval_assistant/assistant_evals_utils.py
uptrain/framework/eval_assistant/parse_files_utils.py
uptrain/integrations/__init__.py
uptrain/integrations/__init__.pyi
uptrain/integrations/llama_index.py
uptrain/integrations/promptfoo.py
uptrain/integrations/promptfoo_utils.py
uptrain/operators/__init__.py
uptrain/operators/__init__.pyi
uptrain/operators/base.py
uptrain/operators/chart.py
uptrain/operators/clustering.py
uptrain/operators/drift.py
uptrain/operators/embs.py
uptrain/operators/metrics.py
uptrain/operators/similarity.py
uptrain/operators/table.py
uptrain/operators/code/__init__.py
uptrain/operators/code/detection.py
uptrain/operators/code/sql.py
uptrain/operators/embedding/__init__.py
uptrain/operators/embedding/embedding.py
uptrain/operators/embedding/vector_search.py
uptrain/operators/io/__init__.py
uptrain/operators/io/base.py
uptrain/operators/io/bq.py
uptrain/operators/io/duck.py
uptrain/operators/io/excel.py
uptrain/operators/io/mongodb.py
uptrain/operators/language/__init__.py
uptrain/operators/language/bleu.py
uptrain/operators/language/context_quality.py
uptrain/operators/language/conversation.py
uptrain/operators/language/custom.py
uptrain/operators/language/factual_accuracy.py
uptrain/operators/language/generation.py
uptrain/operators/language/grammar.py
uptrain/operators/language/guideline.py
uptrain/operators/language/jailbreak.py
uptrain/operators/language/language_quality.py
uptrain/operators/language/llm.py
uptrain-0.7.1.dist-info/LICENSE
uptrain-0.7.1.dist-info/METADATA
uptrain-0.7.1.dist-info/WHEEL
uptrain-0.7.1.dist-info/entry_points.txt
uptrain-0.7.1.dist-info/top_level.txt
uptrain-0.7.1.dist-info/RECORD
