Metadata-Version: 2.1
Name: uptrain
Version: 0.7.1
Summary: UpTrain - tool to evaluate LLM applications on aspects like factual accuracy, response quality, retrieval quality, tonality, etc.
Maintainer-email: UpTrain AI Team <oss@uptrain.ai>
License: Apache-2.0
Project-URL: Homepage, https://uptrain.ai
Project-URL: Repository, https://github.com/uptrain-ai/uptrain
Keywords: uptrain,ai,LLM,evaluation,hallucinations,observability,response quality
Classifier: Development Status :: 5 - Production/Stable
Classifier: Intended Audience :: Developers
Classifier: Topic :: Software Development :: Build Tools
Classifier: License :: OSI Approved :: Apache Software License
Classifier: Programming Language :: Python :: 3.9
Classifier: Programming Language :: Python :: 3.10
Classifier: Programming Language :: Python :: 3.11
License-File: LICENSE
Requires-Dist: pydantic
Requires-Dist: pydantic-settings
Requires-Dist: loguru
Requires-Dist: lazy-loader
Requires-Dist: networkx
Requires-Dist: polars >=0.18
Requires-Dist: pandas
Requires-Dist: numpy >=1.23.0
Requires-Dist: httpx >=0.24.1
Requires-Dist: plotly >=5.0.0
Requires-Dist: aiolimiter >=1.1
Requires-Dist: openai >=1.6.1
Requires-Dist: fsspec
Requires-Dist: litellm
Requires-Dist: pyyaml
Requires-Dist: json5
Requires-Dist: python-docx
Requires-Dist: pymupdf
Requires-Dist: faiss-cpu
Provides-Extra: test
Requires-Dist: pytest >=7.0 ; extra == 'test'
